xmind2xls/__about__.py
xmind2xls/__init__.py
xmind2xls/cli.py
xmind2xls/const.py
xmind2xls/excel.py
xmind2xls/metadata.py
xmind2xls/parser.py
xmind2xls/testlink.py
xmind2xls/utils.py
xmind2xls/zentao.py
xmind2xls-1.0.4.dist-info/METADATA
xmind2xls-1.0.4.dist-info/WHEEL
xmind2xls-1.0.4.dist-info/entry_points.txt
xmind2xls-1.0.4.dist-info/top_level.txt
xmind2xls-1.0.4.dist-info/RECORD
