Metadata-Version: 2.1
Name: xmind2xls
Version: 1.0.4
Summary: Xmind2Xlsx基于Python实现，提供了一个高效测试用例设计的解决方案！
Home-page: https://github.com/taoyu0429/xmid2excel
Author: taoyu
Author-email: 1126931536@qq.com
License: UNKNOWN
Platform: UNKNOWN
Classifier: Programming Language :: Python :: 3
Classifier: License :: OSI Approved :: MIT License
Classifier: Operating System :: OS Independent
Requires-Python: >=3.0, <4
Requires-Dist: xmind
Requires-Dist: openpyxl
